README.md
setup.py
ExpDerive/__init__.py
ExpDerive.egg-info/PKG-INFO
ExpDerive.egg-info/SOURCES.txt
ExpDerive.egg-info/dependency_links.txt
ExpDerive.egg-info/requires.txt
ExpDerive.egg-info/top_level.txt